gum/__init__.py
gum/__main__.py
gum/dem.py
gum/gen.py
gum/gum.py
gum/utl.py
gum/viz.py
gum/gum-jsx/gum.js
gum/gum-jsx/fonts/IBMPlexMono-Regular.ttf
gum/gum-jsx/fonts/IBMPlexSans-Variable.ttf
gum_jsx-0.4.dist-info/METADATA
gum_jsx-0.4.dist-info/WHEEL
gum_jsx-0.4.dist-info/top_level.txt
gum_jsx-0.4.dist-info/RECORD
