Metadata-Version: 2.4
Name: gum-jsx
Version: 0.4
Summary: Python wrapper for gum.jsx, a language for creating vector graphics
Author: Douglas Hanley
License: MIT
Project-URL: Homepage, https://github.com/CompendiumLabs/gum.py
Requires-Python: >=3.8
